vcons/__init__.py
vcons/vcons.py
vcons-1.0.1.dist-info/LICENSE
vcons-1.0.1.dist-info/METADATA
vcons-1.0.1.dist-info/WHEEL
vcons-1.0.1.dist-info/top_level.txt
vcons-1.0.1.dist-info/RECORD
