Metadata-Version: 2.1
Name: vcons
Version: 1.0.1
Summary: A small package to count number of vowels and consonants in a string
Home-page: https://github.com/Ratheshprabakar/vcons
Author: Rathesh Prabakar
Author-email: ratheshprabakar@gmail.com
License: UNKNOWN
Platform: UNKNOWN
Classifier: Programming Language :: Python :: 3
Classifier: License :: OSI Approved :: MIT License
Classifier: Operating System :: OS Independent
Requires-Python: >=3.6
